CHANGES.txt
README.txt
buildout.cfg
setup.py
src/z3c/__init__.py
src/z3c.listjs.egg-info/PKG-INFO
src/z3c.listjs.egg-info/SOURCES.txt
src/z3c.listjs.egg-info/dependency_links.txt
src/z3c.listjs.egg-info/namespace_packages.txt
src/z3c.listjs.egg-info/not-zip-safe
src/z3c.listjs.egg-info/requires.txt
src/z3c.listjs.egg-info/top_level.txt
src/z3c/listjs/__init__.py
src/z3c/listjs/configure.zcml
src/z3c/listjs/ftesting.zcml
src/z3c/listjs/ftests.py
src/z3c/listjs/listjswidget.pt
src/z3c/listjs/testing.py
src/z3c/listjs/widget.py
src/z3c/listjs/resources/down.gif
src/z3c/listjs/resources/listjs.css
src/z3c/listjs/resources/listjs.js
src/z3c/listjs/resources/up.gif