Metadata-Version: 1.0
Name: z3c.listjs
Version: 1.0a2
Summary: A formlib list widget that uses Javascript
Home-page: UNKNOWN
Author: Martijn Faassen
Author-email: faassen@startifact.com
License: ZPL 2.1
Keywords: zope3 form widget
Platform: UNKNOWN
Classifier: Development Status :: 3 - Alpha
Classifier: Environment :: Web Environment
Classifier: Intended Audience :: Developers
Classifier: License :: OSI Approved :: Zope Public License
Classifier: Programming Language :: Python
Classifier: Natural Language :: English
Classifier: Operating System :: OS Independent
Classifier: Topic :: Internet :: WWW/HTTP
Classifier: Framework :: Zope3
